Metadata-Version: 2.1
Name: wyscoutapi
Version: 0.0.1
Summary: An extremely basic wrapper for the Wyscout data API
Home-page: https://github.com/Torvaney/statsbombapi
Author: Ben Torvaney
Author-email: torvaney@protonmail.com
License: GPLv3+
Platform: UNKNOWN
Requires-Python: >=3.7
License-File: LICENSE.txt
